regmod/__init__.py
regmod/_typing.py
regmod/function.py
regmod/optimizer.py
regmod/parameter.py
regmod/prior.py
regmod/utils.py
regmod/variable.py
regmod/composite_models/__init__.py
regmod/composite_models/base.py
regmod/composite_models/chain.py
regmod/composite_models/collections.py
regmod/composite_models/composite.py
regmod/composite_models/interface.py
regmod/composite_models/node.py
regmod/composite_models/tree.py
regmod/models/__init__.py
regmod/models/binomial.py
regmod/models/gaussian.py
regmod/models/model.py
regmod/models/negativebinomial.py
regmod/models/pogit.py
regmod/models/poisson.py
regmod/models/tobit.py
regmod/models/utils.py
regmod/models/weibull.py
regmod-0.2.2.dist-info/LICENSE
regmod-0.2.2.dist-info/METADATA
regmod-0.2.2.dist-info/WHEEL
regmod-0.2.2.dist-info/top_level.txt
regmod-0.2.2.dist-info/RECORD
