Metadata-Version: 2.1
Name: regmod
Version: 0.2.2
Summary: General regression models
Author-email: IHME Math Sciences <ihme.math.sciences@gmail.com>
License: BSD 2-Clause License
Project-URL: stash, https://github.com/ihmeuw-msca/regmod
Requires-Python: >=3.10
License-File: LICENSE
Requires-Dist: numpy
Requires-Dist: scipy
Requires-Dist: pandas
Requires-Dist: xspline ==0.0.7
Requires-Dist: msca
Requires-Dist: jax
Requires-Dist: jaxlib
Provides-Extra: test
Requires-Dist: pytest ; extra == 'test'
